catbox_api/__init__.py
catbox_api/catboxAPI.py
catbox_api-1.3.dist-info/LICENSE.txt
catbox_api-1.3.dist-info/METADATA
catbox_api-1.3.dist-info/WHEEL
catbox_api-1.3.dist-info/top_level.txt
catbox_api-1.3.dist-info/RECORD
