Metadata-Version: 2.1
Name: catbox-api
Version: 1.3
Summary: A Python wrapper for the Catbox.moe API.
Home-page: https://github.com/andrei-cb/catbox_api/
Author: Andrei
Author-email: andrei-cb0@pm.me
License: AGPL-3.0-only
Project-URL: Documentation, https://github.com/andrei-cb/catbox_api/
Platform: any
Classifier: Development Status :: 4 - Beta
Classifier: Programming Language :: Python
License-File: LICENSE.txt
Requires-Dist: requests >=2.0
Requires-Dist: importlib-metadata ; python_version < "3.8"
Provides-Extra: testing
Requires-Dist: setuptools ; extra == 'testing'
Requires-Dist: pytest ; extra == 'testing'
Requires-Dist: pytest-cov ; extra == 'testing'
